[
    {
        "name": "曹操",
        "time": "汉"
    },
    {
        "name": "屈原",
        "time": "战国"
    },
    {
        "name": "宋玉",
        "time": "战国"
    },
    {
        "name": "景差",
        "time": "战国"
    },
    {
        "name": "贾谊",
        "time": "汉"
    },
    {
        "name": "淮南小山",
        "time": "汉"
    },
    {
        "name": "东方朔",
        "time": "汉"
    },
    {
        "name": "庄忌",
        "time": "汉"
    },
    {
        "name": "王褒",
        "time": "汉"
    },
    {
        "name": "刘向",
        "time": "汉"
    },
    {
        "name": "王逸",
        "time": "汉"
    },
    {
        "name": "和岘",
        "time": "宋"
    },
    {
        "name": "王禹",
        "time": "宋"
    },
    {
        "name": "苏易简",
        "time": "宋"
    },
    {
        "name": "寇准",
        "time": "宋"
    },
    {
        "name": "钱惟演",
        "time": "宋"
    },
    {
        "name": "陈尧佐",
        "time": "宋"
    },
    {
        "name": "潘阆",
        "time": "宋"
    },
    {
        "name": "丁谓",
        "time": "宋"
    },
    {
        "name": "林逋",
        "time": "宋"
    },
    {
        "name": "杨亿",
        "time": "宋"
    },
    {
        "name": "陈亚",
        "time": "宋"
    },
    {
        "name": "夏竦",
        "time": "宋"
    },
    {
        "name": "聂冠卿",
        "time": "宋"
    },
    {
        "name": "李遵",
        "time": "宋"
    },
    {
        "name": "范仲淹",
        "time": "宋"
    },
    {
        "name": "沈邈",
        "time": "宋"
    },
    {
        "name": "杨适1",
        "time": "宋"
    },
    {
        "name": "柳永",
        "time": "宋"
    },
    {
        "name": "张先",
        "time": "宋"
    },
    {
        "name": "晏殊",
        "time": "宋"
    },
    {
        "name": "滕宗谅",
        "time": "宋"
    },
    {
        "name": "张",
        "time": "宋"
    },
    {
        "name": "王益",
        "time": "宋"
    },
    {
        "name": "石延年",
        "time": "宋"
    },
    {
        "name": "关咏",
        "time": "宋"
    },
    {
        "name": "刘潜",
        "time": "宋"
    },
    {
        "name": "李冠",
        "time": "宋"
    },
    {
        "name": "谢绛",
        "time": "宋"
    },
    {
        "name": "宋祁",
        "time": "宋"
    },
    {
        "name": "贾昌朝",
        "time": "宋"
    },
    {
        "name": "尹洙",
        "time": "宋"
    },
    {
        "name": "梅尧臣",
        "time": "宋"
    },
    {
        "name": "叶清臣",
        "time": "宋"
    },
    {
        "name": "吴感",
        "time": "宋"
    },
    {
        "name": "文彦博",
        "time": "宋"
    },
    {
        "name": "欧阳修",
        "time": "宋"
    },
    {
        "name": "荣",
        "time": "宋"
    },
    {
        "name": "王琪",
        "time": "宋"
    },
    {
        "name": "陈凤仪",
        "time": "宋"
    },
    {
        "name": "苏舜钦",
        "time": "宋"
    },
    {
        "name": "解",
        "time": "宋"
    },
    {
        "name": "韩琦",
        "time": "宋"
    },
    {
        "name": "沈唐",
        "time": "宋"
    },
    {
        "name": "杜安世",
        "time": "宋"
    },
    {
        "name": "赵",
        "time": "宋"
    },
    {
        "name": "刘几",
        "time": "宋"
    },
    {
        "name": "元绛",
        "time": "宋"
    },
    {
        "name": "程师孟",
        "time": "宋"
    },
    {
        "name": "陈朴",
        "time": "宋"
    },
    {
        "name": "张伯端",
        "time": "宋"
    },
    {
        "name": "卢氏",
        "time": "宋"
    },
    {
        "name": "刘述",
        "time": "宋"
    },
    {
        "name": "赵祯",
        "time": "宋"
    },
    {
        "name": "王拱辰",
        "time": "宋"
    },
    {
        "name": "蔡襄",
        "time": "宋"
    },
    {
        "name": "韩绛",
        "time": "宋"
    },
    {
        "name": "李师中",
        "time": "宋"
    },
    {
        "name": "蔡挺",
        "time": "宋"
    },
    {
        "name": "王益柔",
        "time": "宋"
    },
    {
        "name": "韩维",
        "time": "宋"
    },
    {
        "name": "曾巩",
        "time": "宋"
    },
    {
        "name": "司马光",
        "time": "宋"
    },
    {
        "name": "苏氏",
        "time": "宋"
    },
    {
        "name": "刘敞",
        "time": "宋"
    },
    {
        "name": "王",
        "time": "宋"
    },
    {
        "name": "韩缜",
        "time": "宋"
    },
    {
        "name": "韩缜姬",
        "time": "宋"
    },
    {
        "name": "裴湘",
        "time": "宋"
    },
    {
        "name": "阮逸女",
        "time": "宋"
    },
    {
        "name": "滕甫",
        "time": "宋"
    },
    {
        "name": "王安石",
        "time": "宋"
    },
    {
        "name": "吴氏1",
        "time": "宋"
    },
    {
        "name": "吴师孟",
        "time": "宋"
    },
    {
        "name": "俞紫芝",
        "time": "宋"
    },
    {
        "name": "郑獬",
        "time": "宋"
    },
    {
        "name": "强至",
        "time": "宋"
    },
    {
        "name": "沈注",
        "time": "宋"
    },
    {
        "name": "蒲宗孟",
        "time": "宋"
    },
    {
        "name": "陈汝羲",
        "time": "宋"
    },
    {
        "name": "汪辅之",
        "time": "宋"
    },
    {
        "name": "范纯仁",
        "time": "宋"
    },
    {
        "name": "张才翁",
        "time": "宋"
    },
    {
        "name": "寿涯禅师",
        "time": "宋"
    },
    {
        "name": "章",
        "time": "宋"
    },
    {
        "name": "徐积",
        "time": "宋"
    },
    {
        "name": "沈括",
        "time": "宋"
    },
    {
        "name": "范宽之",
        "time": "宋"
    },
    {
        "name": "方资",
        "time": "宋"
    },
    {
        "name": "王安国",
        "time": "宋"
    },
    {
        "name": "孙洙",
        "time": "宋"
    },
    {
        "name": "李清臣",
        "time": "宋"
    },
    {
        "name": "韦骧",
        "time": "宋"
    },
    {
        "name": "圆禅师",
        "time": "宋"
    },
    {
        "name": "则禅师",
        "time": "宋"
    },
    {
        "name": "陈偕",
        "time": "宋"
    },
    {
        "name": "晏几道",
        "time": "宋"
    },
    {
        "name": "王观",
        "time": "宋"
    },
    {
        "name": "王安礼",
        "time": "宋"
    },
    {
        "name": "张舜民",
        "time": "宋"
    },
    {
        "name": "曾布",
        "time": "宋"
    },
    {
        "name": "魏夫人",
        "time": "宋"
    },
    {
        "name": "王仲甫",
        "time": "宋"
    },
    {
        "name": "孙浩然",
        "time": "宋"
    },
    {
        "name": "王诜",
        "time": "宋"
    },
    {
        "name": "陈济翁",
        "time": "宋"
    },
    {
        "name": "苏轼",
        "time": "宋"
    },
    {
        "name": "郭讵",
        "time": "宋"
    },
    {
        "name": "李之仪",
        "time": "宋"
    },
    {
        "name": "蔡确",
        "time": "宋"
    },
    {
        "name": "许将",
        "time": "宋"
    },
    {
        "name": "郑无党",
        "time": "宋"
    },
    {
        "name": "陈",
        "time": "宋"
    },
    {
        "name": "苏辙",
        "time": "宋"
    },
    {
        "name": "陈睦",
        "time": "宋"
    },
    {
        "name": "马成",
        "time": "宋"
    },
    {
        "name": "李婴",
        "time": "宋"
    },
    {
        "name": "王齐愈",
        "time": "宋"
    },
    {
        "name": "王齐叟",
        "time": "宋"
    },
    {
        "name": "舒氏",
        "time": "宋"
    },
    {
        "name": "琴操",
        "time": "宋"
    },
    {
        "name": "舒亶",
        "time": "宋"
    },
    {
        "name": "范祖禹",
        "time": "宋"
    },
    {
        "name": "孔平仲",
        "time": "宋"
    },
    {
        "name": "了元",
        "time": "宋"
    },
    {
        "name": "太尉夫人",
        "time": "宋"
    },
    {
        "name": "郭祥正",
        "time": "宋"
    },
    {
        "name": "董",
        "time": "宋"
    },
    {
        "name": "丁仙现",
        "time": "宋"
    },
    {
        "name": "刘泾",
        "time": "宋"
    },
    {
        "name": "黄裳",
        "time": "宋"
    },
    {
        "name": "王清观",
        "time": "宋"
    },
    {
        "name": "熊则轩",
        "time": "宋"
    },
    {
        "name": "阮溪",
        "time": "宋"
    },
    {
        "name": "危西麓",
        "time": "宋"
    },
    {
        "name": "汪元量",
        "time": "宋"
    },
    {
        "name": "王学文",
        "time": "宋"
    },
    {
        "name": "王清惠",
        "time": "宋"
    },
    {
        "name": "章丽贞",
        "time": "宋"
    },
    {
        "name": "袁正真",
        "time": "宋"
    },
    {
        "name": "金德淑",
        "time": "宋"
    },
    {
        "name": "连妙淑",
        "time": "宋"
    },
    {
        "name": "黄静淑",
        "time": "宋"
    },
    {
        "name": "陶明淑",
        "time": "宋"
    },
    {
        "name": "柳华淑",
        "time": "宋"
    },
    {
        "name": "杨慧淑",
        "time": "宋"
    },
    {
        "name": "华清淑",
        "time": "宋"
    },
    {
        "name": "梅顺淑",
        "time": "宋"
    },
    {
        "name": "吴昭淑",
        "time": "宋"
    },
    {
        "name": "周容淑",
        "time": "宋"
    },
    {
        "name": "吴淑真",
        "time": "宋"
    },
    {
        "name": "张琼英",
        "time": "宋"
    },
    {
        "name": "詹玉",
        "time": "宋"
    },
    {
        "name": "王沂孙",
        "time": "宋"
    },
    {
        "name": "黄公绍",
        "time": "宋"
    },
    {
        "name": "彭履道",
        "time": "宋"
    },
    {
        "name": "韦居安",
        "time": "宋"
    },
    {
        "name": "柴元彪",
        "time": "宋"
    },
    {
        "name": "东冈",
        "time": "宋"
    },
    {
        "name": "范文",
        "time": "宋"
    },
    {
        "name": "叶李",
        "time": "宋"
    },
    {
        "name": "梁栋",
        "time": "宋"
    },
    {
        "name": "莫",
        "time": "宋"
    },
    {
        "name": "姚云文",
        "time": "宋"
    },
    {
        "name": "赵必",
        "time": "宋"
    },
    {
        "name": "黎廷瑞",
        "time": "宋"
    },
    {
        "name": "李震",
        "time": "宋"
    },
    {
        "name": "陈纪",
        "time": "宋"
    },
    {
        "name": "仇远",
        "time": "宋"
    },
    {
        "name": "董嗣杲",
        "time": "宋"
    },
    {
        "name": "高远",
        "time": "宋"
    },
    {
        "name": "杨均",
        "time": "宋"
    },
    {
        "name": "胡幼黄",
        "time": "宋"
    },
    {
        "name": "熊禾",
        "time": "宋"
    },
    {
        "name": "詹无咎",
        "time": "宋"
    },
    {
        "name": "王槐建",
        "time": "宋"
    },
    {
        "name": "刘应李",
        "time": "宋"
    },
    {
        "name": "王梦应",
        "time": "宋"
    },
    {
        "name": "孙锐",
        "time": "宋"
    },
    {
        "name": "李琳",
        "time": "宋"
    },
    {
        "name": "醴陵士人",
        "time": "宋"
    },
    {
        "name": "褚生",
        "time": "宋"
    },
    {
        "name": "徐君宝妻",
        "time": "宋"
    },
    {
        "name": "刘氏",
        "time": "宋"
    },
    {
        "name": "无闻翁",
        "time": "宋"
    },
    {
        "name": "杨氏",
        "time": "宋"
    },
    {
        "name": "张淑芳",
        "time": "宋"
    },
    {
        "name": "王易简",
        "time": "宋"
    },
    {
        "name": "冯应瑞",
        "time": "宋"
    },
    {
        "name": "唐艺孙",
        "time": "宋"
    },
    {
        "name": "吕同老",
        "time": "宋"
    },
    {
        "name": "李居仁",
        "time": "宋"
    },
    {
        "name": "唐珏",
        "time": "宋"
    },
    {
        "name": "赵汝钠",
        "time": "宋"
    },
    {
        "name": "曹稆孙",
        "time": "宋"
    },
    {
        "name": "林横舟",
        "time": "宋"
    },
    {
        "name": "杨舜举",
        "time": "宋"
    },
    {
        "name": "危复之",
        "time": "宋"
    },
    {
        "name": "罗志仁",
        "time": "宋"
    },
    {
        "name": "曾寅孙",
        "time": "宋"
    },
    {
        "name": "沈钦",
        "time": "宋"
    },
    {
        "name": "刘沆",
        "time": "宋"
    },
    {
        "name": "止禅师",
        "time": "宋"
    },
    {
        "name": "蒋捷",
        "time": "宋"
    },
    {
        "name": "张炎",
        "time": "宋"
    },
    {
        "name": "韩信同",
        "time": "宋"
    },
    {
        "name": "王炎午",
        "time": "宋"
    },
    {
        "name": "徐瑞",
        "time": "宋"
    },
    {
        "name": "王去疾",
        "time": "宋"
    },
    {
        "name": "刘将孙",
        "time": "宋"
    },
    {
        "name": "陈恕可",
        "time": "宋"
    },
    {
        "name": "陈深",
        "time": "宋"
    },
    {
        "name": "刘铉",
        "time": "宋"
    },
    {
        "name": "梁明夫",
        "time": "宋"
    },
    {
        "name": "梅坡",
        "time": "宋"
    },
    {
        "name": "徐观国",
        "time": "宋"
    },
    {
        "name": "某邑妓",
        "time": "宋"
    },
    {
        "name": "阮郎中",
        "time": "宋"
    },
    {
        "name": "吴某",
        "time": "宋"
    },
    {
        "name": "俞克成",
        "time": "宋"
    },
    {
        "name": "胡浩然",
        "time": "宋"
    },
    {
        "name": "宋丰之",
        "time": "宋"
    },
    {
        "name": "孙夫人",
        "time": "宋"
    },
    {
        "name": "陈若晦",
        "time": "宋"
    },
    {
        "name": "徐一初",
        "time": "宋"
    },
    {
        "name": "吴叔",
        "time": "宋"
    },
    {
        "name": "陈彦章妻",
        "time": "宋"
    },
    {
        "name": "郑文妻",
        "time": "宋"
    },
    {
        "name": "刘鼎臣妻",
        "time": "宋"
    },
    {
        "name": "张任国",
        "time": "宋"
    },
    {
        "name": "福建士子",
        "time": "宋"
    },
    {
        "name": "钟辰翁",
        "time": "宋"
    },
    {
        "name": "萧仲芮",
        "time": "宋"
    },
    {
        "name": "陈士豪",
        "time": "宋"
    },
    {
        "name": "赵通判",
        "time": "宋"
    },
    {
        "name": "赵汝恂",
        "time": "宋"
    },
    {
        "name": "石麟",
        "time": "宋"
    },
    {
        "name": "黄通判",
        "time": "宋"
    },
    {
        "name": "高子芳",
        "time": "宋"
    },
    {
        "name": "萧仲",
        "time": "宋"
    },
    {
        "name": "熊德修",
        "time": "宋"
    },
    {
        "name": "范飞",
        "time": "宋"
    },
    {
        "name": "程和仲",
        "time": "宋"
    },
    {
        "name": "咏槐",
        "time": "宋"
    },
    {
        "name": "陈梦协",
        "time": "宋"
    },
    {
        "name": "刘清之",
        "time": "宋"
    },
    {
        "name": "王绍",
        "time": "宋"
    },
    {
        "name": "程节斋",
        "time": "宋"
    },
    {
        "name": "张仲殊",
        "time": "宋"
    },
    {
        "name": "吴氏2",
        "time": "宋"
    },
    {
        "name": "吴编修",
        "time": "宋"
    },
    {
        "name": "赵龙图",
        "time": "宋"
    },
    {
        "name": "竹林亭长",
        "time": "宋"
    },
    {
        "name": "杨樵云",
        "time": "宋"
    },
    {
        "name": "刘应雄",
        "time": "宋"
    },
    {
        "name": "曾隶",
        "time": "宋"
    },
    {
        "name": "黄水村",
        "time": "宋"
    },
    {
        "name": "姜个翁",
        "time": "宋"
    },
    {
        "name": "彭芳远",
        "time": "宋"
    },
    {
        "name": "戴山隐",
        "time": "宋"
    },
    {
        "name": "李裕翁",
        "time": "宋"
    },
    {
        "name": "龙端是",
        "time": "宋"
    },
    {
        "name": "萧东父",
        "time": "宋"
    },
    {
        "name": "王从叔",
        "time": "宋"
    },
    {
        "name": "吴元可",
        "time": "宋"
    },
    {
        "name": "李太古",
        "time": "宋"
    },
    {
        "name": "黄子行",
        "time": "宋"
    },
    {
        "name": "龙紫蓬",
        "time": "宋"
    },
    {
        "name": "萧允之",
        "time": "宋"
    },
    {
        "name": "段宏章",
        "time": "宋"
    },
    {
        "name": "刘贵翁",
        "time": "宋"
    },
    {
        "name": "黄霁宇",
        "time": "宋"
    },
    {
        "name": "刘天迪",
        "time": "宋"
    },
    {
        "name": "张半湖",
        "time": "宋"
    },
    {
        "name": "刘景翔",
        "time": "宋"
    },
    {
        "name": "周伯阳",
        "time": "宋"
    },
    {
        "name": "尹公远",
        "time": "宋"
    },
    {
        "name": "李天骥",
        "time": "宋"
    },
    {
        "name": "刘应几",
        "time": "宋"
    },
    {
        "name": "周孚先",
        "time": "宋"
    },
    {
        "name": "彭泰翁",
        "time": "宋"
    },
    {
        "name": "曾允元",
        "time": "宋"
    },
    {
        "name": "朱元夫",
        "time": "宋"
    },
    {
        "name": "邵桂子",
        "time": "宋"
    },
    {
        "name": "彭子翔",
        "time": "宋"
    },
    {
        "name": "百兰",
        "time": "宋"
    },
    {
        "name": "丁持正",
        "time": "宋"
    },
    {
        "name": "李石才",
        "time": "宋"
    },
    {
        "name": "魏顺之",
        "time": "宋"
    },
    {
        "name": "伍梅城",
        "time": "宋"
    },
    {
        "name": "丁几仲",
        "time": "宋"
    },
    {
        "name": "禅峰",
        "time": "宋"
    },
    {
        "name": "刘涧谷",
        "time": "宋"
    },
    {
        "name": "游稚仙",
        "time": "宋"
    },
    {
        "name": "李团湖",
        "time": "宋"
    },
    {
        "name": "黄诚之",
        "time": "宋"
    },
    {
        "name": "熊子默",
        "time": "宋"
    },
    {
        "name": "陈惟哲",
        "time": "宋"
    },
    {
        "name": "欧阳朝阳",
        "time": "宋"
    },
    {
        "name": "碧虚",
        "time": "宋"
    },
    {
        "name": "彭正大",
        "time": "宋"
    },
    {
        "name": "叶巽斋",
        "time": "宋"
    },
    {
        "name": "铁笔翁",
        "time": "宋"
    },
    {
        "name": "刘性初",
        "time": "宋"
    },
    {
        "name": "刘学颜",
        "time": "宋"
    },
    {
        "name": "江史君",
        "time": "宋"
    },
    {
        "name": "徐架阁",
        "time": "宋"
    },
    {
        "name": "立斋",
        "time": "宋"
    },
    {
        "name": "黄革",
        "time": "宋"
    },
    {
        "name": "陈潜心",
        "time": "宋"
    },
    {
        "name": "罗子",
        "time": "宋"
    },
    {
        "name": "刘公子",
        "time": "宋"
    },
    {
        "name": "三槐",
        "time": "宋"
    },
    {
        "name": "程东湾",
        "time": "宋"
    },
    {
        "name": "胡德芳",
        "time": "宋"
    },
    {
        "name": "赵宰",
        "time": "宋"
    },
    {
        "name": "张宰",
        "time": "宋"
    },
    {
        "name": "梁大年",
        "time": "宋"
    },
    {
        "name": "鼓峰",
        "time": "宋"
    },
    {
        "name": "程霁岩",
        "time": "宋"
    },
    {
        "name": "翠微翁",
        "time": "宋"
    },
    {
        "name": "菊翁",
        "time": "宋"
    },
    {
        "name": "赵佥判",
        "time": "宋"
    },
    {
        "name": "李慧之",
        "time": "宋"
    },
    {
        "name": "留晚香",
        "time": "宋"
    },
    {
        "name": "杨守",
        "time": "宋"
    },
    {
        "name": "草夫人",
        "time": "宋"
    },
    {
        "name": "游慈",
        "time": "宋"
    },
    {
        "name": "静山",
        "time": "宋"
    },
    {
        "name": "刘守",
        "time": "宋"
    },
    {
        "name": "逸民",
        "time": "宋"
    },
    {
        "name": "无何有翁",
        "time": "宋"
    },
    {
        "name": "任翔龙",
        "time": "宋"
    },
    {
        "name": "程梅斋",
        "time": "宋"
    },
    {
        "name": "刘省斋",
        "time": "宋"
    },
    {
        "name": "刘仁父",
        "time": "宋"
    },
    {
        "name": "刘南翁",
        "time": "宋"
    },
    {
        "name": "勿翁",
        "time": "宋"
    },
    {
        "name": "李君行",
        "time": "宋"
    },
    {
        "name": "赋梅",
        "time": "宋"
    },
    {
        "name": "易少夫人",
        "time": "宋"
    },
    {
        "name": "胡平仲",
        "time": "宋"
    },
    {
        "name": "曹遇",
        "time": "宋"
    },
    {
        "name": "白君瑞",
        "time": "宋"
    },
    {
        "name": "贾应",
        "time": "宋"
    },
    {
        "name": "杨元亨",
        "time": "宋"
    },
    {
        "name": "林实之",
        "time": "宋"
    },
    {
        "name": "刘源",
        "time": "宋"
    },
    {
        "name": "曾中思",
        "time": "宋"
    },
    {
        "name": "黄子功",
        "time": "宋"
    },
    {
        "name": "张嗣初",
        "time": "宋"
    },
    {
        "name": "沈明叔",
        "time": "宋"
    },
    {
        "name": "寇寺丞",
        "time": "宋"
    },
    {
        "name": "苏小小",
        "time": "宋"
    },
    {
        "name": "李秀兰",
        "time": "宋"
    },
    {
        "name": "胡夫人",
        "time": "宋"
    },
    {
        "name": "窦夫人",
        "time": "宋"
    },
    {
        "name": "王娇姿",
        "time": "宋"
    },
    {
        "name": "洛阳女",
        "time": "宋"
    },
    {
        "name": "丁羲叟",
        "time": "宋"
    },
    {
        "name": "陶氏",
        "time": "宋"
    },
    {
        "name": "吴奕",
        "time": "宋"
    },
    {
        "name": "杨太尉",
        "time": "宋"
    },
    {
        "name": "李子申",
        "time": "宋"
    },
    {
        "name": "闾丘次杲",
        "time": "宋"
    },
    {
        "name": "危昂霄",
        "time": "宋"
    },
    {
        "name": "万某",
        "time": "宋"
    },
    {
        "name": "蔡士裕",
        "time": "宋"
    },
    {
        "name": "覃怀高",
        "time": "宋"
    },
    {
        "name": "巴州守",
        "time": "宋"
    },
    {
        "name": "江无□",
        "time": "宋"
    },
    {
        "name": "无名氏",
        "time": "宋"
    },
    {
        "name": "葛胜仲",
        "time": "宋"
    },
    {
        "name": "米友仁",
        "time": "宋"
    },
    {
        "name": "曾纡",
        "time": "宋"
    },
    {
        "name": "秦湛",
        "time": "宋"
    },
    {
        "name": "范周",
        "time": "宋"
    },
    {
        "name": "吴则礼",
        "time": "宋"
    },
    {
        "name": "向子諲",
        "time": "宋"
    },
    {
        "name": "刘望之",
        "time": "宋"
    },
    {
        "name": "法常",
        "time": "宋"
    },
    {
        "name": "陆淞",
        "time": "宋"
    },
    {
        "name": "卓世清",
        "time": "宋"
    },
    {
        "name": "李结",
        "time": "宋"
    },
    {
        "name": "向",
        "time": "宋"
    },
    {
        "name": "程大昌",
        "time": "宋"
    },
    {
        "name": "范成大",
        "time": "宋"
    },
    {
        "name": "游次公",
        "time": "宋"
    },
    {
        "name": "赵老",
        "time": "宋"
    },
    {
        "name": "尤袤",
        "time": "宋"
    },
    {
        "name": "谢懋",
        "time": "宋"
    },
    {
        "name": "王质",
        "time": "宋"
    },
    {
        "name": "张孝祥",
        "time": "宋"
    },
    {
        "name": "郭世模",
        "time": "宋"
    },
    {
        "name": "黄仁荣",
        "time": "宋"
    },
    {
        "name": "许左之",
        "time": "宋"
    },
    {
        "name": "黄谈",
        "time": "宋"
    },
    {
        "name": "阎苍舒",
        "time": "宋"
    },
    {
        "name": "崔敦礼",
        "time": "宋"
    },
    {
        "name": "陈造",
        "time": "宋"
    },
    {
        "name": "黄定",
        "time": "宋"
    },
    {
        "name": "王自中",
        "time": "宋"
    },
    {
        "name": "李处全",
        "time": "宋"
    },
    {
        "name": "韩",
        "time": "宋"
    },
    {
        "name": "李廷忠",
        "time": "宋"
    },
    {
        "name": "方千里",
        "time": "宋"
    },
    {
        "name": "吴泳",
        "time": "宋"
    },
    {
        "name": "张景修",
        "time": "宋"
    },
    {
        "name": "黄大临",
        "time": "宋"
    },
    {
        "name": "黄庭坚",
        "time": "宋"
    },
    {
        "name": "贺铸",
        "time": "宋"
    },
    {
        "name": "赵仲御",
        "time": "宋"
    },
    {
        "name": "仲殊",
        "time": "宋"
    },
    {
        "name": "吕本中",
        "time": "宋"
    },
    {
        "name": "毕良史",
        "time": "宋"
    },
    {
        "name": "沈晦",
        "time": "宋"
    },
    {
        "name": "郭章",
        "time": "宋"
    },
    {
        "name": "胡世将",
        "time": "宋"
    },
    {
        "name": "赵鼎",
        "time": "宋"
    },
    {
        "name": "蒋璨",
        "time": "宋"
    },
    {
        "name": "李邴",
        "time": "宋"
    },
    {
        "name": "韦庄",
        "time": "宋"
    },
    {
        "name": "梁意娘",
        "time": "宋"
    },
    {
        "name": "越娘",
        "time": "宋"
    },
    {
        "name": "张师师",
        "time": "宋"
    },
    {
        "name": "钱安安",
        "time": "宋"
    },
    {
        "name": "张商英",
        "time": "宋"
    },
    {
        "name": "徐都尉",
        "time": "宋"
    },
    {
        "name": "崔木",
        "time": "宋"
    },
    {
        "name": "黄舜英",
        "time": "宋"
    },
    {
        "name": "贾奕",
        "time": "宋"
    },
    {
        "name": "窃杯女子",
        "time": "宋"
    },
    {
        "name": "刘",
        "time": "宋"
    },
    {
        "name": "陈义",
        "time": "宋"
    },
    {
        "name": "净端",
        "time": "宋"
    },
    {
        "name": "善珍",
        "time": "宋"
    },
    {
        "name": "李彭",
        "time": "宋"
    },
    {
        "name": "无际道人",
        "time": "宋"
    },
    {
        "name": "朱涣",
        "time": "宋"
    },
    {
        "name": "毕大节",
        "time": "宋"
    },
    {
        "name": "庞籍",
        "time": "宋"
    },
    {
        "name": "周起",
        "time": "宋"
    },
    {
        "name": "杨绘",
        "time": "宋"
    },
    {
        "name": "晁端礼",
        "time": "宋"
    },
    {
        "name": "毛滂",
        "time": "宋"
    },
    {
        "name": "赵鼎臣",
        "time": "宋"
    },
    {
        "name": "吴淑虎",
        "time": "宋"
    },
    {
        "name": "吴叔虎",
        "time": "宋"
    },
    {
        "name": "张伯寿",
        "time": "宋"
    },
    {
        "name": "曹宰",
        "time": "宋"
    },
    {
        "name": "王子容",
        "time": "宋"
    },
    {
        "name": "叶景山",
        "time": "宋"
    },
    {
        "name": "李商英",
        "time": "宋"
    },
    {
        "name": "马伯升",
        "time": "宋"
    },
    {
        "name": "陈克",
        "time": "宋"
    },
    {
        "name": "李清照",
        "time": "宋"
    },
    {
        "name": "莫蒙",
        "time": "宋"
    },
    {
        "name": "宝月",
        "time": "宋"
    },
    {
        "name": "邓肃",
        "time": "宋"
    },
    {
        "name": "曾",
        "time": "宋"
    },
    {
        "name": "严抑",
        "time": "宋"
    },
    {
        "name": "沈长卿",
        "time": "宋"
    },
    {
        "name": "张浚",
        "time": "宋"
    },
    {
        "name": "胡寅",
        "time": "宋"
    },
    {
        "name": "鲁",
        "time": "宋"
    },
    {
        "name": "陆凝之",
        "time": "宋"
    },
    {
        "name": "阳居士",
        "time": "宋"
    },
    {
        "name": "赵士",
        "time": "宋"
    },
    {
        "name": "李朴",
        "time": "宋"
    },
    {
        "name": "温镗",
        "time": "宋"
    },
    {
        "name": "芮烨",
        "time": "宋"
    },
    {
        "name": "傅自得",
        "time": "宋"
    },
    {
        "name": "李鼐",
        "time": "宋"
    },
    {
        "name": "韩元吉",
        "time": "宋"
    },
    {
        "name": "张抡",
        "time": "宋"
    },
    {
        "name": "侯置",
        "time": "宋"
    },
    {
        "name": "赵彦端",
        "time": "宋"
    },
    {
        "name": "芮辉",
        "time": "宋"
    },
    {
        "name": "刘季裴",
        "time": "宋"
    },
    {
        "name": "姜特立",
        "time": "宋"
    },
    {
        "name": "徐叔至",
        "time": "宋"
    },
    {
        "name": "□阳",
        "time": "宋"
    },
    {
        "name": "赵彦逾",
        "time": "宋"
    },
    {
        "name": "卫时敏",
        "time": "宋"
    },
    {
        "name": "高伯达",
        "time": "宋"
    },
    {
        "name": "郝子直",
        "time": "宋"
    },
    {
        "name": "何得之",
        "time": "宋"
    },
    {
        "name": "徐明仲",
        "time": "宋"
    },
    {
        "name": "陈之贤",
        "time": "宋"
    },
    {
        "name": "丁求安",
        "time": "宋"
    },
    {
        "name": "赵师律",
        "time": "宋"
    },
    {
        "name": "赵师严",
        "time": "宋"
    },
    {
        "name": "辛弃疾",
        "time": "宋"
    },
    {
        "name": "沈伯文",
        "time": "宋"
    },
    {
        "name": "钱处仁",
        "time": "宋"
    },
    {
        "name": "李焕",
        "time": "宋"
    },
    {
        "name": "林伯镇",
        "time": "宋"
    },
    {
        "name": "王涣",
        "time": "宋"
    },
    {
        "name": "陈敷",
        "time": "宋"
    },
    {
        "name": "甄良友",
        "time": "宋"
    },
    {
        "name": "郑元秀",
        "time": "宋"
    },
    {
        "name": "黄人杰",
        "time": "宋"
    },
    {
        "name": "石孝友",
        "time": "宋"
    },
    {
        "name": "周云",
        "time": "宋"
    },
    {
        "name": "俞国宝",
        "time": "宋"
    },
    {
        "name": "王孝严",
        "time": "宋"
    },
    {
        "name": "陈晔",
        "time": "宋"
    },
    {
        "name": "邵元实",
        "time": "宋"
    },
    {
        "name": "卑叔文",
        "time": "宋"
    },
    {
        "name": "臧鲁子",
        "time": "宋"
    },
    {
        "name": "陈秉文",
        "time": "宋"
    },
    {
        "name": "谈羲仲",
        "time": "宋"
    },
    {
        "name": "王高",
        "time": "宋"
    },
    {
        "name": "江袤",
        "time": "宋"
    },
    {
        "name": "华岳",
        "time": "宋"
    },
    {
        "name": "赵希蓬",
        "time": "宋"
    },
    {
        "name": "程伯春",
        "time": "宋"
    },
    {
        "name": "赵良玉",
        "time": "宋"
    },
    {
        "name": "赵孟谦",
        "time": "宋"
    },
    {
        "name": "张明中",
        "time": "宋"
    },
    {
        "name": "刘克庄",
        "time": "宋"
    },
    {
        "name": "方岳",
        "time": "宋"
    },
    {
        "name": "郭子正",
        "time": "宋"
    },
    {
        "name": "朱子厚",
        "time": "宋"
    },
    {
        "name": "张埴",
        "time": "宋"
    },
    {
        "name": "丁无悔",
        "time": "宋"
    },
    {
        "name": "杨再可",
        "time": "宋"
    },
    {
        "name": "刘仲讷",
        "time": "宋"
    },
    {
        "name": "蒋思恭",
        "time": "宋"
    },
    {
        "name": "张成可",
        "time": "宋"
    },
    {
        "name": "丁仲远",
        "time": "宋"
    },
    {
        "name": "真知柔",
        "time": "宋"
    },
    {
        "name": "张时甫",
        "time": "宋"
    },
    {
        "name": "李朝卿",
        "time": "宋"
    },
    {
        "name": "谈元范",
        "time": "宋"
    },
    {
        "name": "倪翼周",
        "time": "宋"
    },
    {
        "name": "段倚",
        "time": "宋"
    },
    {
        "name": "贺及",
        "time": "宋"
    },
    {
        "name": "傅伯达",
        "time": "宋"
    },
    {
        "name": "郑达可",
        "time": "宋"
    },
    {
        "name": "臧馀庆",
        "time": "宋"
    },
    {
        "name": "胡于",
        "time": "宋"
    },
    {
        "name": "申国章",
        "time": "宋"
    },
    {
        "name": "陈日章",
        "time": "宋"
    },
    {
        "name": "李景良",
        "time": "宋"
    },
    {
        "name": "张思济",
        "time": "宋"
    },
    {
        "name": "李夫人",
        "time": "宋"
    },
    {
        "name": "张藻",
        "time": "宋"
    },
    {
        "name": "胡文卿",
        "time": "宋"
    },
    {
        "name": "杨道居",
        "time": "宋"
    },
    {
        "name": "史佐尧",
        "time": "宋"
    },
    {
        "name": "徐去非",
        "time": "宋"
    },
    {
        "name": "舒大成",
        "time": "宋"
    },
    {
        "name": "贾少卿",
        "time": "宋"
    },
    {
        "name": "陆汉广",
        "time": "宋"
    },
    {
        "name": "王阜民",
        "time": "宋"
    },
    {
        "name": "霍安人",
        "time": "宋"
    },
    {
        "name": "希叟",
        "time": "宋"
    },
    {
        "name": "沈元实",
        "time": "宋"
    },
    {
        "name": "游子蒙",
        "time": "宋"
    },
    {
        "name": "贾逋",
        "time": "宋"
    },
    {
        "name": "吴文若",
        "time": "宋"
    },
    {
        "name": "去非",
        "time": "宋"
    },
    {
        "name": "潘熊飞",
        "time": "宋"
    },
    {
        "name": "黄庭佐",
        "time": "宋"
    },
    {
        "name": "赵□",
        "time": "宋"
    },
    {
        "name": "吴氏3",
        "time": "宋"
    },
    {
        "name": "张元干",
        "time": "宋"
    },
    {
        "name": "林淳",
        "time": "宋"
    },
    {
        "name": "廖行之",
        "time": "宋"
    },
    {
        "name": "京镗",
        "time": "宋"
    },
    {
        "name": "张震",
        "time": "宋"
    },
    {
        "name": "王炎2",
        "time": "宋"
    },
    {
        "name": "梅娇",
        "time": "宋"
    },
    {
        "name": "杏俏",
        "time": "宋"
    },
    {
        "name": "苏小娘",
        "time": "宋"
    },
    {
        "name": "张魁",
        "time": "宋"
    },
    {
        "name": "张枢密",
        "time": "宋"
    },
    {
        "name": "申二官人",
        "time": "宋"
    },
    {
        "name": "杨岛仙",
        "time": "宋"
    },
    {
        "name": "吴德远",
        "time": "宋"
    },
    {
        "name": "连静女",
        "time": "宋"
    },
    {
        "name": "楚娘",
        "time": "宋"
    },
    {
        "name": "谢福娘",
        "time": "宋"
    },
    {
        "name": "张时",
        "time": "宋"
    },
    {
        "name": "双渐",
        "time": "宋"
    },
    {
        "name": "黄夫人",
        "time": "宋"
    },
    {
        "name": "刘使君",
        "time": "宋"
    },
    {
        "name": "李氏2",
        "time": "宋"
    },
    {
        "name": "朱希真",
        "time": "宋"
    },
    {
        "name": "张幼谦",
        "time": "宋"
    },
    {
        "name": "罗惜惜",
        "time": "宋"
    },
    {
        "name": "萧回",
        "time": "宋"
    },
    {
        "name": "春娘",
        "time": "宋"
    },
    {
        "name": "张生2",
        "time": "宋"
    },
    {
        "name": "郑云娘",
        "time": "宋"
    },
    {
        "name": "吕岩",
        "time": "宋"
    },
    {
        "name": "海哥",
        "time": "宋"
    },
    {
        "name": "何仙姑",
        "time": "宋"
    },
    {
        "name": "宋媛",
        "time": "宋"
    },
    {
        "name": "吴城小龙女",
        "time": "宋"
    },
    {
        "name": "蔡真人",
        "time": "宋"
    },
    {
        "name": "懒堂女子",
        "time": "宋"
    },
    {
        "name": "巫山神女",
        "time": "宋"
    },
    {
        "name": "玉英",
        "time": "宋"
    },
    {
        "name": "紫姑",
        "time": "宋"
    },
    {
        "name": "清源真君",
        "time": "宋"
    },
    {
        "name": "李季萼",
        "time": "宋"
    },
    {
        "name": "随车娘子",
        "time": "宋"
    },
    {
        "name": "玉真",
        "time": "宋"
    },
    {
        "name": "乩仙",
        "time": "宋"
    },
    {
        "name": "琴精",
        "time": "宋"
    },
    {
        "name": "珍娘",
        "time": "宋"
    },
    {
        "name": "刘焘",
        "time": "宋"
    },
    {
        "name": "田为",
        "time": "宋"
    },
    {
        "name": "崔中",
        "time": "宋"
    },
    {
        "name": "何锄翁",
        "time": "宋"
    },
    {
        "name": "衣白山人",
        "time": "宋"
    },
    {
        "name": "叶梦得",
        "time": "宋"
    },
    {
        "name": "黄叔达",
        "time": "宋"
    },
    {
        "name": "盼盼",
        "time": "宋"
    },
    {
        "name": "曾肇",
        "time": "宋"
    },
    {
        "name": "郑仅",
        "time": "宋"
    },
    {
        "name": "蔡京",
        "time": "宋"
    },
    {
        "name": "苏琼",
        "time": "宋"
    },
    {
        "name": "李元膺",
        "time": "宋"
    },
    {
        "name": "吕南公",
        "time": "宋"
    },
    {
        "name": "赵顼",
        "time": "宋"
    },
    {
        "name": "吕希纯",
        "time": "宋"
    },
    {
        "name": "喻陟",
        "time": "宋"
    },
    {
        "name": "朱服",
        "time": "宋"
    },
    {
        "name": "丁注",
        "time": "宋"
    },
    {
        "name": "时彦",
        "time": "宋"
    },
    {
        "name": "廖正一",
        "time": "宋"
    },
    {
        "name": "董武子",
        "time": "宋"
    },
    {
        "name": "哑女",
        "time": "宋"
    },
    {
        "name": "秦观",
        "time": "宋"
    },
    {
        "name": "米芾",
        "time": "宋"
    },
    {
        "name": "李甲",
        "time": "宋"
    },
    {
        "name": "赵令",
        "time": "宋"
    },
    {
        "name": "晁补之",
        "time": "宋"
    },
    {
        "name": "陈师道",
        "time": "宋"
    },
    {
        "name": "青幕子妇",
        "time": "宋"
    },
    {
        "name": "张耒",
        "time": "宋"
    },
    {
        "name": "侯蒙",
        "time": "宋"
    },
    {
        "name": "周邦彦",
        "time": "宋"
    },
    {
        "name": "刘山老",
        "time": "宋"
    },
    {
        "name": "邵伯温",
        "time": "宋"
    },
    {
        "name": "李",
        "time": "宋"
    },
    {
        "name": "孔夷",
        "time": "宋"
    },
    {
        "name": "孔矩",
        "time": "宋"
    },
    {
        "name": "邹浩",
        "time": "宋"
    },
    {
        "name": "曾诞",
        "time": "宋"
    },
    {
        "name": "李坦然",
        "time": "宋"
    },
    {
        "name": "阮阅",
        "time": "宋"
    },
    {
        "name": "赵企",
        "time": "宋"
    },
    {
        "name": "汪存",
        "time": "宋"
    },
    {
        "name": "谢逸",
        "time": "宋"
    },
    {
        "name": "夏倪",
        "time": "宋"
    },
    {
        "name": "晁冲之",
        "time": "宋"
    },
    {
        "name": "苏庠",
        "time": "宋"
    },
    {
        "name": "祖可",
        "time": "宋"
    },
    {
        "name": "蔡",
        "time": "宋"
    },
    {
        "name": "张阁",
        "time": "宋"
    },
    {
        "name": "宇文元质",
        "time": "宋"
    },
    {
        "name": "范致虚",
        "time": "宋"
    },
    {
        "name": "郑少微",
        "time": "宋"
    },
    {
        "name": "李新",
        "time": "宋"
    },
    {
        "name": "欧阳辟",
        "time": "宋"
    },
    {
        "name": "司马",
        "time": "宋"
    },
    {
        "name": "王重",
        "time": "宋"
    },
    {
        "name": "某两地",
        "time": "宋"
    },
    {
        "name": "王采",
        "time": "宋"
    },
    {
        "name": "周纯",
        "time": "宋"
    },
    {
        "name": "曹希蕴",
        "time": "宋"
    },
    {
        "name": "廖刚",
        "time": "宋"
    },
    {
        "name": "韩嘉彦",
        "time": "宋"
    },
    {
        "name": "谢",
        "time": "宋"
    },
    {
        "name": "沈蔚",
        "time": "宋"
    },
    {
        "name": "唐庚",
        "time": "宋"
    },
    {
        "name": "惠洪",
        "time": "宋"
    },
    {
        "name": "吕颐浩",
        "time": "宋"
    },
    {
        "name": "苏过",
        "time": "宋"
    },
    {
        "name": "陆蕴",
        "time": "宋"
    },
    {
        "name": "谢克家",
        "time": "宋"
    },
    {
        "name": "李德载",
        "time": "宋"
    },
    {
        "name": "赵子发",
        "time": "宋"
    },
    {
        "name": "徐俯",
        "time": "宋"
    },
    {
        "name": "王安中",
        "time": "宋"
    },
    {
        "name": "张继先",
        "time": "宋"
    },
    {
        "name": "江衍",
        "time": "宋"
    },
    {
        "name": "周铢",
        "time": "宋"
    },
    {
        "name": "王赏",
        "time": "宋"
    },
    {
        "name": "李光",
        "time": "宋"
    },
    {
        "name": "张生1",
        "time": "宋"
    },
    {
        "name": "江纬",
        "time": "宋"
    },
    {
        "name": "美奴",
        "time": "宋"
    },
    {
        "name": "张扩",
        "time": "宋"
    },
    {
        "name": "赵子崧",
        "time": "宋"
    },
    {
        "name": "鉴堂",
        "time": "宋"
    },
    {
        "name": "梅窗",
        "time": "宋"
    },
    {
        "name": "欧阳",
        "time": "宋"
    },
    {
        "name": "刘一止",
        "time": "宋"
    },
    {
        "name": "汪藻",
        "time": "宋"
    },
    {
        "name": "曹组",
        "time": "宋"
    },
    {
        "name": "万俟咏",
        "time": "宋"
    },
    {
        "name": "徐伸",
        "time": "宋"
    },
    {
        "name": "江汉",
        "time": "宋"
    },
    {
        "name": "田中行",
        "time": "宋"
    },
    {
        "name": "赵温之",
        "time": "宋"
    },
    {
        "name": "王庭",
        "time": "宋"
    },
    {
        "name": "薛式",
        "time": "宋"
    },
    {
        "name": "朱敦复",
        "time": "宋"
    },
    {
        "name": "朱敦儒",
        "time": "宋"
    },
    {
        "name": "孙觌",
        "time": "宋"
    },
    {
        "name": "慕容卿妻",
        "time": "宋"
    },
    {
        "name": "周紫芝",
        "time": "宋"
    },
    {
        "name": "李弥逊",
        "time": "宋"
    },
    {
        "name": "王以宁",
        "time": "宋"
    },
    {
        "name": "吕渭老",
        "time": "宋"
    },
    {
        "name": "林季仲",
        "time": "宋"
    },
    {
        "name": "王之道",
        "time": "宋"
    },
    {
        "name": "曹勋",
        "time": "宋"
    },
    {
        "name": "吴舜选",
        "time": "宋"
    },
    {
        "name": "赵桓",
        "time": "宋"
    },
    {
        "name": "刘子",
        "time": "宋"
    },
    {
        "name": "何大圭",
        "time": "宋"
    },
    {
        "name": "胡铨",
        "time": "宋"
    },
    {
        "name": "宋先生",
        "time": "宋"
    },
    {
        "name": "叶适",
        "time": "宋"
    },
    {
        "name": "刘褒",
        "time": "宋"
    },
    {
        "name": "章良能",
        "time": "宋"
    },
    {
        "name": "熊以宁",
        "time": "宋"
    },
    {
        "name": "詹克爱",
        "time": "宋"
    },
    {
        "name": "李寅仲",
        "time": "宋"
    },
    {
        "name": "高观国",
        "time": "宋"
    },
    {
        "name": "魏了翁",
        "time": "宋"
    },
    {
        "name": "吴文英",
        "time": "宋"
    },
    {
        "name": "莫将",
        "time": "宋"
    },
    {
        "name": "邵博",
        "time": "宋"
    },
    {
        "name": "赵佶",
        "time": "宋"
    },
    {
        "name": "侯彭老",
        "time": "宋"
    },
    {
        "name": "李纲",
        "time": "宋"
    },
    {
        "name": "胡舜陟",
        "time": "宋"
    },
    {
        "name": "李祁",
        "time": "宋"
    },
    {
        "name": "叶祖义",
        "time": "宋"
    },
    {
        "name": "左誉",
        "time": "宋"
    },
    {
        "name": "吕直夫",
        "time": "宋"
    },
    {
        "name": "杨景",
        "time": "宋"
    },
    {
        "name": "范智闻",
        "time": "宋"
    },
    {
        "name": "蒋元龙",
        "time": "宋"
    },
    {
        "name": "周格非",
        "time": "宋"
    },
    {
        "name": "程邻",
        "time": "宋"
    },
    {
        "name": "何籀",
        "time": "宋"
    },
    {
        "name": "廖世美",
        "time": "宋"
    },
    {
        "name": "李元卓",
        "time": "宋"
    },
    {
        "name": "张方仲",
        "time": "宋"
    },
    {
        "name": "查",
        "time": "宋"
    },
    {
        "name": "李敦诗",
        "time": "宋"
    },
    {
        "name": "康仲伯",
        "time": "宋"
    },
    {
        "name": "程过",
        "time": "宋"
    },
    {
        "name": "张纲",
        "time": "宋"
    },
    {
        "name": "吴穆仲",
        "time": "宋"
    },
    {
        "name": "杨适2",
        "time": "宋"
    },
    {
        "name": "韩驹",
        "time": "宋"
    },
    {
        "name": "颜博文",
        "time": "宋"
    },
    {
        "name": "沈与求",
        "time": "宋"
    },
    {
        "name": "陈东",
        "time": "宋"
    },
    {
        "name": "姚孝宁",
        "time": "宋"
    },
    {
        "name": "胡松年",
        "time": "宋"
    },
    {
        "name": "李持正",
        "time": "宋"
    },
    {
        "name": "王道亨",
        "time": "宋"
    },
    {
        "name": "江致和",
        "time": "宋"
    },
    {
        "name": "韩璜",
        "time": "宋"
    },
    {
        "name": "李邦献",
        "time": "宋"
    },
    {
        "name": "宋齐愈",
        "time": "宋"
    },
    {
        "name": "宋江",
        "time": "宋"
    },
    {
        "name": "袁",
        "time": "宋"
    },
    {
        "name": "连仲宣",
        "time": "宋"
    },
    {
        "name": "邢俊臣",
        "time": "宋"
    },
    {
        "name": "幼卿",
        "time": "宋"
    },
    {
        "name": "蒋氏女",
        "time": "宋"
    },
    {
        "name": "蔡楠",
        "time": "宋"
    },
    {
        "name": "李久善",
        "time": "宋"
    },
    {
        "name": "苏仲及",
        "time": "宋"
    },
    {
        "name": "赵耆孙",
        "time": "宋"
    },
    {
        "name": "费时举",
        "time": "宋"
    },
    {
        "name": "刘均国",
        "time": "宋"
    },
    {
        "name": "权无染",
        "time": "宋"
    },
    {
        "name": "南山居士",
        "time": "宋"
    },
    {
        "name": "郭仲宣",
        "time": "宋"
    },
    {
        "name": "邵叔齐",
        "time": "宋"
    },
    {
        "name": "李子正",
        "time": "宋"
    },
    {
        "name": "房舜卿",
        "time": "宋"
    },
    {
        "name": "石耆翁",
        "time": "宋"
    },
    {
        "name": "杜安道",
        "time": "宋"
    },
    {
        "name": "史远道",
        "time": "宋"
    },
    {
        "name": "郭仲循",
        "time": "宋"
    },
    {
        "name": "范梦龙",
        "time": "宋"
    },
    {
        "name": "薛几圣",
        "time": "宋"
    },
    {
        "name": "马咸",
        "time": "宋"
    },
    {
        "name": "洪皓",
        "time": "宋"
    },
    {
        "name": "蔡伸",
        "time": "宋"
    },
    {
        "name": "何",
        "time": "宋"
    },
    {
        "name": "郑刚中",
        "time": "宋"
    },
    {
        "name": "韩世忠",
        "time": "宋"
    },
    {
        "name": "黄大舆",
        "time": "宋"
    },
    {
        "name": "王灼",
        "time": "宋"
    },
    {
        "name": "陈袭善",
        "time": "宋"
    },
    {
        "name": "曾乾曜",
        "time": "宋"
    },
    {
        "name": "孙",
        "time": "宋"
    },
    {
        "name": "如晦",
        "time": "宋"
    },
    {
        "name": "孙舣",
        "time": "宋"
    },
    {
        "name": "潘汾",
        "time": "宋"
    },
    {
        "name": "李重元",
        "time": "宋"
    },
    {
        "name": "李玉",
        "time": "宋"
    },
    {
        "name": "吴淑姬1",
        "time": "宋"
    },
    {
        "name": "柳富",
        "time": "宋"
    },
    {
        "name": "王幼玉",
        "time": "宋"
    },
    {
        "name": "李生",
        "time": "宋"
    },
    {
        "name": "谭意哥",
        "time": "宋"
    },
    {
        "name": "李氏1",
        "time": "宋"
    },
    {
        "name": "花仲胤",
        "time": "宋"
    },
    {
        "name": "花仲胤妻",
        "time": "宋"
    },
    {
        "name": "刘浚",
        "time": "宋"
    },
    {
        "name": "施酒监",
        "time": "宋"
    },
    {
        "name": "乐婉",
        "time": "宋"
    },
    {
        "name": "虞某",
        "time": "宋"
    },
    {
        "name": "巴谈",
        "time": "宋"
    },
    {
        "name": "杨师纯",
        "time": "宋"
    },
    {
        "name": "杨端臣",
        "time": "宋"
    },
    {
        "name": "聂胜琼",
        "time": "宋"
    },
    {
        "name": "赵才卿",
        "time": "宋"
    },
    {
        "name": "任",
        "time": "宋"
    },
    {
        "name": "都下妓",
        "time": "宋"
    },
    {
        "name": "陈与义",
        "time": "宋"
    },
    {
        "name": "杜大中妾",
        "time": "宋"
    },
    {
        "name": "刘彤",
        "time": "宋"
    },
    {
        "name": "僧儿",
        "time": "宋"
    },
    {
        "name": "胡仔",
        "time": "宋"
    },
    {
        "name": "王昂",
        "time": "宋"
    },
    {
        "name": "谢明远",
        "time": "宋"
    },
    {
        "name": "张焘",
        "time": "宋"
    },
    {
        "name": "姚述尧1",
        "time": "宋"
    },
    {
        "name": "董颖",
        "time": "宋"
    },
    {
        "name": "潘良贵",
        "time": "宋"
    },
    {
        "name": "董德元",
        "time": "宋"
    },
    {
        "name": "冯时行",
        "time": "宋"
    },
    {
        "name": "朱松",
        "time": "宋"
    },
    {
        "name": "朱翌",
        "time": "宋"
    },
    {
        "name": "陈康伯",
        "time": "宋"
    },
    {
        "name": "欧阳澈",
        "time": "宋"
    },
    {
        "name": "张表臣",
        "time": "宋"
    },
    {
        "name": "吴亿",
        "time": "宋"
    },
    {
        "name": "刘袤",
        "time": "宋"
    },
    {
        "name": "杨无咎",
        "time": "宋"
    },
    {
        "name": "俞处",
        "time": "宋"
    },
    {
        "name": "岳飞",
        "time": "宋"
    },
    {
        "name": "邵缉",
        "time": "宋"
    },
    {
        "name": "吴芾",
        "time": "宋"
    },
    {
        "name": "孙道绚",
        "time": "宋"
    },
    {
        "name": "何蓑衣道人",
        "time": "宋"
    },
    {
        "name": "史浩",
        "time": "宋"
    },
    {
        "name": "仲并",
        "time": "宋"
    },
    {
        "name": "赵构",
        "time": "宋"
    },
    {
        "name": "崔若砺",
        "time": "宋"
    },
    {
        "name": "高登",
        "time": "宋"
    },
    {
        "name": "闻人武子",
        "time": "宋"
    },
    {
        "name": "关注",
        "time": "宋"
    },
    {
        "name": "李石",
        "time": "宋"
    },
    {
        "name": "康与之",
        "time": "宋"
    },
    {
        "name": "曾觌",
        "time": "宋"
    },
    {
        "name": "黄公度",
        "time": "宋"
    },
    {
        "name": "黄童",
        "time": "宋"
    },
    {
        "name": "倪",
        "time": "宋"
    },
    {
        "name": "王之望",
        "time": "宋"
    },
    {
        "name": "葛立方",
        "time": "宋"
    },
    {
        "name": "魏杞",
        "time": "宋"
    },
    {
        "name": "陈知柔",
        "time": "宋"
    },
    {
        "name": "王识",
        "time": "宋"
    },
    {
        "name": "许庭",
        "time": "宋"
    },
    {
        "name": "邵某",
        "time": "宋"
    },
    {
        "name": "陈祖安",
        "time": "宋"
    },
    {
        "name": "王十朋",
        "time": "宋"
    },
    {
        "name": "刘大辨",
        "time": "宋"
    },
    {
        "name": "吴淑姬2",
        "time": "宋"
    },
    {
        "name": "程先",
        "time": "宋"
    },
    {
        "name": "朱耆寿",
        "time": "宋"
    },
    {
        "name": "石安民",
        "time": "宋"
    },
    {
        "name": "刘镇1",
        "time": "宋"
    },
    {
        "name": "魏之",
        "time": "宋"
    },
    {
        "name": "曾协",
        "time": "宋"
    },
    {
        "name": "郑庶",
        "time": "宋"
    },
    {
        "name": "曾逮",
        "time": "宋"
    },
    {
        "name": "王炎1",
        "time": "宋"
    },
    {
        "name": "毛并",
        "time": "宋"
    },
    {
        "name": "洪适",
        "time": "宋"
    },
    {
        "name": "黄宰",
        "time": "宋"
    },
    {
        "name": "朱淑真",
        "time": "宋"
    },
    {
        "name": "沈瀛",
        "time": "宋"
    },
    {
        "name": "杨万里",
        "time": "宋"
    },
    {
        "name": "某教授",
        "time": "宋"
    },
    {
        "name": "陈居仁",
        "time": "宋"
    },
    {
        "name": "李洪",
        "time": "宋"
    },
    {
        "name": "李漳",
        "time": "宋"
    },
    {
        "name": "李泳",
        "time": "宋"
    },
    {
        "name": "朱熹",
        "time": "宋"
    },
    {
        "name": "黄铢",
        "time": "宋"
    },
    {
        "name": "高宣教",
        "time": "宋"
    },
    {
        "name": "严蕊",
        "time": "宋"
    },
    {
        "name": "晦庵",
        "time": "宋"
    },
    {
        "name": "徐逸",
        "time": "宋"
    },
    {
        "name": "沈端节",
        "time": "宋"
    },
    {
        "name": "韩仙姑",
        "time": "宋"
    },
    {
        "name": "周颉",
        "time": "宋"
    },
    {
        "name": "王彭年",
        "time": "宋"
    },
    {
        "name": "李伯虎",
        "time": "宋"
    },
    {
        "name": "丘",
        "time": "宋"
    },
    {
        "name": "朱颜",
        "time": "宋"
    },
    {
        "name": "吕胜己",
        "time": "宋"
    },
    {
        "name": "唐致政",
        "time": "宋"
    },
    {
        "name": "楼锷",
        "time": "宋"
    },
    {
        "name": "林外",
        "time": "宋"
    },
    {
        "name": "梁安世",
        "time": "宋"
    },
    {
        "name": "黄岩叟",
        "time": "宋"
    },
    {
        "name": "富扌肃",
        "time": "宋"
    },
    {
        "name": "邵怀英",
        "time": "宋"
    },
    {
        "name": "赵长卿",
        "time": "宋"
    },
    {
        "name": "罗愿",
        "time": "宋"
    },
    {
        "name": "楼钥",
        "time": "宋"
    },
    {
        "name": "张良臣",
        "time": "宋"
    },
    {
        "name": "王千秋",
        "time": "宋"
    },
    {
        "name": "李吕",
        "time": "宋"
    },
    {
        "name": "陈从古",
        "time": "宋"
    },
    {
        "name": "姚宽",
        "time": "宋"
    },
    {
        "name": "刘珙",
        "time": "宋"
    },
    {
        "name": "黄格",
        "time": "宋"
    },
    {
        "name": "汤思退",
        "time": "宋"
    },
    {
        "name": "张仲宇",
        "time": "宋"
    },
    {
        "name": "李流谦",
        "time": "宋"
    },
    {
        "name": "洪迈",
        "time": "宋"
    },
    {
        "name": "赵缩手",
        "time": "宋"
    },
    {
        "name": "张风子",
        "time": "宋"
    },
    {
        "name": "张珍奴",
        "time": "宋"
    },
    {
        "name": "洪惠英",
        "time": "宋"
    },
    {
        "name": "何作善",
        "time": "宋"
    },
    {
        "name": "刘之翰",
        "time": "宋"
    },
    {
        "name": "周某",
        "time": "宋"
    },
    {
        "name": "太学诸生",
        "time": "宋"
    },
    {
        "name": "仪珏",
        "time": "宋"
    },
    {
        "name": "袁去华",
        "time": "宋"
    },
    {
        "name": "朱雍",
        "time": "宋"
    },
    {
        "name": "晁公武",
        "time": "宋"
    },
    {
        "name": "林仰",
        "time": "宋"
    },
    {
        "name": "邵伯雍",
        "time": "宋"
    },
    {
        "name": "黄中辅",
        "time": "宋"
    },
    {
        "name": "郑闻",
        "time": "宋"
    },
    {
        "name": "曹冠",
        "time": "宋"
    },
    {
        "name": "葛郯",
        "time": "宋"
    },
    {
        "name": "姚述尧2",
        "time": "宋"
    },
    {
        "name": "石敦夫",
        "time": "宋"
    },
    {
        "name": "甄龙友",
        "time": "宋"
    },
    {
        "name": "范端臣",
        "time": "宋"
    },
    {
        "name": "韦能谦",
        "time": "宋"
    },
    {
        "name": "耿时举",
        "time": "宋"
    },
    {
        "name": "管鉴",
        "time": "宋"
    },
    {
        "name": "吴儆",
        "time": "宋"
    },
    {
        "name": "陆游",
        "time": "宋"
    },
    {
        "name": "唐婉",
        "time": "宋"
    },
    {
        "name": "陆游妾某氏",
        "time": "宋"
    },
    {
        "name": "贾逸祖",
        "time": "宋"
    },
    {
        "name": "蜀妓",
        "time": "宋"
    },
    {
        "name": "周必大",
        "time": "宋"
    },
    {
        "name": "周辉",
        "time": "宋"
    },
    {
        "name": "舒邦佐",
        "time": "宋"
    },
    {
        "name": "张孝忠",
        "time": "宋"
    },
    {
        "name": "方有开",
        "time": "宋"
    },
    {
        "name": "许及之",
        "time": "宋"
    },
    {
        "name": "傅大询",
        "time": "宋"
    },
    {
        "name": "刘德秀",
        "time": "宋"
    },
    {
        "name": "吴镒",
        "time": "宋"
    },
    {
        "name": "杨冠卿",
        "time": "宋"
    },
    {
        "name": "崔敦诗",
        "time": "宋"
    },
    {
        "name": "赵汝愚",
        "time": "宋"
    },
    {
        "name": "赵善扛",
        "time": "宋"
    },
    {
        "name": "赵善括",
        "time": "宋"
    },
    {
        "name": "程垓",
        "time": "宋"
    },
    {
        "name": "虞俦",
        "time": "宋"
    },
    {
        "name": "徐似道",
        "time": "宋"
    },
    {
        "name": "徐安国",
        "time": "宋"
    }
]